baseball_data/__init__.py
baseball_data/player.py
baseball_data/team.py
baseball_data-0.0.0.1.dist-info/METADATA
baseball_data-0.0.0.1.dist-info/WHEEL
baseball_data-0.0.0.1.dist-info/top_level.txt
baseball_data-0.0.0.1.dist-info/RECORD
